enexis_friends_quiz/__init__.py
enexis_friends_quiz/__main__.py
enexis_friends_quiz/guessing.py
enexis_friends_quiz/utils/logger.py
enexis_friends_quiz-100.0.0.dist-info/LICENSE
enexis_friends_quiz-100.0.0.dist-info/METADATA
enexis_friends_quiz-100.0.0.dist-info/WHEEL
enexis_friends_quiz-100.0.0.dist-info/RECORD
