Metadata-Version: 2.1
Name: enexis-friends-quiz
Version: 100.0.0
Summary: Super quiz!
Home-page: https://github.com/mariushelf/enexis_friends_quiz
License: MIT
Author: Marius Helf
Author-email: marius.helf@enexis.nl
Requires-Python: >=3.9,<4.0
Classifier: Development Status :: 4 - Beta
Classifier: License :: OSI Approved :: MIT License
Classifier: Programming Language :: Python :: 3
Classifier: Programming Language :: Python :: 3.9
Classifier: Programming Language :: Python :: 3.10
Classifier: Programming Language :: Python :: 3.11
Classifier: Programming Language :: Python :: 3.10
Classifier: Programming Language :: Python :: 3.11
Classifier: Programming Language :: Python :: 3.9
Classifier: Programming Language :: Python :: Implementation :: PyPy
Requires-Dist: numpy (>=1.24.2,<2.0.0)
Project-URL: Documentation, https://enexis_friends_quiz.readthedocs.io
Project-URL: Repository, https://github.com/mariushelf/enexis_friends_quiz
